image_indexer/__init__.py
image_indexer/__main__.py
image_indexer/cli.py
image_indexer/config.py
image_indexer/indexer.py
image_indexer/utils.py
siglip2_image_indexer-1.0.2.dist-info/licenses/LICENSE
siglip2_image_indexer-1.0.2.dist-info/METADATA
siglip2_image_indexer-1.0.2.dist-info/WHEEL
siglip2_image_indexer-1.0.2.dist-info/entry_points.txt
siglip2_image_indexer-1.0.2.dist-info/top_level.txt
siglip2_image_indexer-1.0.2.dist-info/RECORD
