Metadata-Version: 2.4
Name: siglip2-image-indexer
Version: 1.0.2
Summary: A command-line tool to index images using SigLIP2 models and generate embeddings
Author-email: Yudivián Almeida Cruz <yudivian@gmail.com>
License-Expression: MIT
Project-URL: Homepage, https://github.com/yudivian/siglip2-image-indexer
Project-URL: Bug Tracker, https://github.com/yudivian/siglip2-image-indexer/issues
Requires-Python: >=3.9
License-File: LICENSE
Requires-Dist: torch>=2.0.0
Requires-Dist: transformers>=4.30.0
Requires-Dist: Pillow>=10.0.0
Requires-Dist: PyYAML>=6.0
Requires-Dist: tqdm>=4.60.0
Requires-Dist: pillow-heif>=0.10.0
Requires-Dist: huggingface_hub>=0.20.0
Requires-Dist: piexif>=1.1.3
Provides-Extra: ui
Requires-Dist: streamlit>=1.0; extra == "ui"
Dynamic: license-file
